key_changer/__init__.py
key_changer/__main__.py
key_changer/key_changer.py
key_changer/keyboard_map.py
key_changer-3.0.dist-info/LICENSE
key_changer-3.0.dist-info/METADATA
key_changer-3.0.dist-info/WHEEL
key_changer-3.0.dist-info/top_level.txt
key_changer-3.0.dist-info/RECORD
