Metadata-Version: 2.1
Name: key-changer
Version: 3.0
Summary: change keyboard character
Home-page: https://github.com/keegang6705/en-th-keyboard-translator
Author: keegang_6705
Author-email: darunphobwi@gmail.com
License: MIT
Platform: UNKNOWN
Requires-Python: >=3.0
License-File: LICENSE
